indictrans2/__init__.py
indictrans2/constants.py
indictrans2/translator.py
indictrans2/user_agents.py
indictrans2_ai4bharat-0.1.0.dist-info/licenses/LICENSE
indictrans2_ai4bharat-0.1.0.dist-info/METADATA
indictrans2_ai4bharat-0.1.0.dist-info/WHEEL
indictrans2_ai4bharat-0.1.0.dist-info/top_level.txt
indictrans2_ai4bharat-0.1.0.dist-info/RECORD
