Metadata-Version: 2.4
Name: indictrans2-ai4bharat
Version: 0.1.0
Summary: Python package for Indian language translation using AI4Bharat's IndicTrans2 API
Home-page: https://github.com/yourusername/indictrans2-ai4bharat
Author: Indian Language Translation Tool
Author-email: your.email@example.com
Project-URL: Documentation, https://github.com/yourusername/indictrans2-ai4bharat#readme
Project-URL: Source, https://github.com/yourusername/indictrans2-ai4bharat
Project-URL: Tracker, https://github.com/yourusername/indictrans2-ai4bharat/issues
Keywords: translation,indian languages,nlp,ai4bharat,indic languages,language detection
Classifier: Development Status :: 4 - Beta
Classifier: Intended Audience :: Developers
Classifier: License :: OSI Approved :: MIT License
Classifier: Operating System :: OS Independent
Classifier: Programming Language :: Python :: 3
Classifier: Programming Language :: Python :: 3.7
Classifier: Programming Language :: Python :: 3.8
Classifier: Programming Language :: Python :: 3.9
Classifier: Programming Language :: Python :: 3.10
Classifier: Topic :: Software Development :: Libraries :: Python Modules
Classifier: Topic :: Text Processing :: Linguistic
Requires-Python: >=3.7
License-File: LICENSE
Requires-Dist: requests>=2.25.1
Requires-Dist: typing>=3.7.4
Requires-Dist: urllib3>=1.26.0
Requires-Dist: langdetect>=1.0.9
Dynamic: author
Dynamic: author-email
Dynamic: classifier
Dynamic: description
Dynamic: description-content-type
Dynamic: home-page
Dynamic: keywords
Dynamic: license-file
Dynamic: project-url
Dynamic: requires-dist
Dynamic: requires-python
Dynamic: summary
